audio2midi/__init__.py
audio2midi/basic_pitch_pitch_detector.py
audio2midi/crepe_pitch_detector.py
audio2midi/crepe_pitch_detector_tf.py
audio2midi/librosa_pitch_detector.py
audio2midi/magenta_music_transcription.py
audio2midi/melodia_pitch_detector.py
audio2midi/mt3_music_transcription.py
audio2midi/pop2piano.py
audio2midi/py.typed
audio2midi/violin_pitch_detector.py
audio2midi/yourmt3_music_transcription.py
audio2midi-0.15.0.dist-info/METADATA
audio2midi-0.15.0.dist-info/WHEEL
audio2midi-0.15.0.dist-info/RECORD
