Metadata-Version: 2.4
Name: audio2midi
Version: 0.15.0
Summary: Audio To Midi
Author-email: dummyjenil <dummyjenil@gmail.com>
Provides-Extra: all
Requires-Dist: essentia; extra == 'all'
Requires-Dist: hmmlearn; extra == 'all'
Requires-Dist: huggingface-hub; extra == 'all'
Requires-Dist: keras; extra == 'all'
Requires-Dist: librosa; extra == 'all'
Requires-Dist: mir-eval; extra == 'all'
Requires-Dist: mt3-audio2midi; extra == 'all'
Requires-Dist: nest-asyncio; extra == 'all'
Requires-Dist: nnaudio; extra == 'all'
Requires-Dist: numpy==1.26.4; extra == 'all'
Requires-Dist: pretty-midi; extra == 'all'
Requires-Dist: pretty-midi-fix; extra == 'all'
Requires-Dist: resampy; extra == 'all'
Requires-Dist: scipy; extra == 'all'
Requires-Dist: tensorflow; extra == 'all'
Requires-Dist: torch; extra == 'all'
Requires-Dist: torchaudio; extra == 'all'
Requires-Dist: transformers; extra == 'all'
Requires-Dist: vamp; extra == 'all'
Requires-Dist: yourmt3; extra == 'all'
Provides-Extra: basic-pitch-pitch-detector
Requires-Dist: huggingface-hub; extra == 'basic-pitch-pitch-detector'
Requires-Dist: librosa; extra == 'basic-pitch-pitch-detector'
Requires-Dist: nnaudio; extra == 'basic-pitch-pitch-detector'
Requires-Dist: numpy; extra == 'basic-pitch-pitch-detector'
Requires-Dist: pretty-midi-fix; extra == 'basic-pitch-pitch-detector'
Requires-Dist: scipy; extra == 'basic-pitch-pitch-detector'
Requires-Dist: torch; extra == 'basic-pitch-pitch-detector'
Provides-Extra: crepe-pitch-detector
Requires-Dist: hmmlearn; extra == 'crepe-pitch-detector'
Requires-Dist: huggingface-hub; extra == 'crepe-pitch-detector'
Requires-Dist: librosa; extra == 'crepe-pitch-detector'
Requires-Dist: numpy; extra == 'crepe-pitch-detector'
Requires-Dist: pretty-midi-fix; extra == 'crepe-pitch-detector'
Requires-Dist: tensorflow; extra == 'crepe-pitch-detector'
Requires-Dist: torch; extra == 'crepe-pitch-detector'
Requires-Dist: tqdm; extra == 'crepe-pitch-detector'
Provides-Extra: crepe-pitch-detector-tf
Requires-Dist: hmmlearn; extra == 'crepe-pitch-detector-tf'
Requires-Dist: huggingface-hub; extra == 'crepe-pitch-detector-tf'
Requires-Dist: keras; extra == 'crepe-pitch-detector-tf'
Requires-Dist: librosa; extra == 'crepe-pitch-detector-tf'
Requires-Dist: numpy; extra == 'crepe-pitch-detector-tf'
Requires-Dist: pretty-midi-fix; extra == 'crepe-pitch-detector-tf'
Requires-Dist: tensorflow; extra == 'crepe-pitch-detector-tf'
Provides-Extra: librosa-pitch-detector
Requires-Dist: librosa; extra == 'librosa-pitch-detector'
Requires-Dist: numpy; extra == 'librosa-pitch-detector'
Requires-Dist: pretty-midi-fix; extra == 'librosa-pitch-detector'
Provides-Extra: magenta-music-transcription
Requires-Dist: huggingface-hub; extra == 'magenta-music-transcription'
Requires-Dist: librosa; extra == 'magenta-music-transcription'
Requires-Dist: numpy; extra == 'magenta-music-transcription'
Requires-Dist: pretty-midi-fix; extra == 'magenta-music-transcription'
Requires-Dist: tensorflow; extra == 'magenta-music-transcription'
Provides-Extra: melodia-pitch-detector
Requires-Dist: huggingface-hub; extra == 'melodia-pitch-detector'
Requires-Dist: librosa; extra == 'melodia-pitch-detector'
Requires-Dist: numpy; extra == 'melodia-pitch-detector'
Requires-Dist: pretty-midi-fix; extra == 'melodia-pitch-detector'
Requires-Dist: scipy; extra == 'melodia-pitch-detector'
Requires-Dist: vamp; extra == 'melodia-pitch-detector'
Provides-Extra: mt3-music-transcription
Requires-Dist: mt3-audio2midi; extra == 'mt3-music-transcription'
Requires-Dist: nest-asyncio; extra == 'mt3-music-transcription'
Provides-Extra: pop2piano
Requires-Dist: essentia; extra == 'pop2piano'
Requires-Dist: huggingface-hub; extra == 'pop2piano'
Requires-Dist: librosa; extra == 'pop2piano'
Requires-Dist: numpy==1.26.4; extra == 'pop2piano'
Requires-Dist: pretty-midi; extra == 'pop2piano'
Requires-Dist: pretty-midi-fix; extra == 'pop2piano'
Requires-Dist: resampy; extra == 'pop2piano'
Requires-Dist: scipy; extra == 'pop2piano'
Requires-Dist: torch; extra == 'pop2piano'
Requires-Dist: transformers; extra == 'pop2piano'
Provides-Extra: violin-pitch-detector
Requires-Dist: huggingface-hub; extra == 'violin-pitch-detector'
Requires-Dist: librosa; extra == 'violin-pitch-detector'
Requires-Dist: mir-eval; extra == 'violin-pitch-detector'
Requires-Dist: numpy; extra == 'violin-pitch-detector'
Requires-Dist: pretty-midi-fix; extra == 'violin-pitch-detector'
Requires-Dist: scipy; extra == 'violin-pitch-detector'
Requires-Dist: torch; extra == 'violin-pitch-detector'
Requires-Dist: torchaudio; extra == 'violin-pitch-detector'
Provides-Extra: yourmt3-music-transcription
Requires-Dist: yourmt3; extra == 'yourmt3-music-transcription'
